zanestear/__init__.py
zanestear/one.py
zanestear/two.py
zanestear-0.0.5.dist-info/LICENSE
zanestear-0.0.5.dist-info/METADATA
zanestear-0.0.5.dist-info/WHEEL
zanestear-0.0.5.dist-info/top_level.txt
zanestear-0.0.5.dist-info/RECORD
