Metadata-Version: 2.1
Name: zanestear
Version: 0.0.5
Summary: ZaneStear Test
Home-page: https://github.com/ZaneStear/
Author: ZaneStear
Author-email: 1030349525@qq.com
License: MIT
Platform: UNKNOWN
License-File: LICENSE
